{
  "title": "World News",
  "link": "https://www.reddit.com/r/worldnews/.rss",
  "description": "A place for major news from around the world, excluding US-internal news.",
  "language": "",
  "generator": "",
  "published": "2024-06-02T23:12:46.000Z",
  "entries": [
    {
      "id": "t3_1d64sx9",
      "title": "/r/WorldNews Live Thread: Russian Invasion of Ukraine Day 830, Part 1 (Thread #976)",
      "link": "https://www.reddit.com/r/worldnews/comments/1d64sx9/rworldnews_live_thread_russian_invasion_of/",
      "published": "2024-06-02T04:02:22.000Z",
      "description": "submitted by    /u/WorldNewsMods   [link]   [comments]",
      "summary": "",
      "author": {
        "name": "/u/WorldNewsMods",
        "uri": "https://www.reddit.com/user/WorldNewsMods"
      },
      "category": {
        "@_term": "worldnews",
        "@_label": "r/worldnews"
      }
    },
    {
      "id": "t3_1d5wr4h",
      "title": "/r/WorldNews Live Thread for Israel-Hamas War (Thread #52)",
      "link": "https://www.reddit.com/r/worldnews/comments/1d5wr4h/rworldnews_live_thread_for_israelhamas_war_thread/",
      "published": "2024-06-01T21:01:11.000Z",
      "description": "submitted by    /u/AutoModerator   [link]   [comments]",
      "summary": "",
      "author": {
        "name": "/u/AutoModerator",
        "uri": "https://www.reddit.com/user/AutoModerator"
      },
      "category": {
        "@_term": "worldnews",
        "@_label": "r/worldnews"
      }
    },
    {
      "id": "t3_1d6fyn8",
      "title": "Modi eyes 'super majority' amid fears he will change India's constitution",
      "link": "https://www.reddit.com/r/worldnews/comments/1d6fyn8/modi_eyes_super_majority_amid_fears_he_will/",
      "published": "2024-06-02T15:35:14.000Z",
      "description": "submitted by    /u/TheTelegraph   [link]   [comments]",
      "summary": "",
      "author": {
        "name": "/u/TheTelegraph",
        "uri": "https://www.reddit.com/user/TheTelegraph"
      },
      "category": {
        "@_term": "worldnews",
        "@_label": "r/worldnews"
      }
    },
    {
      "id": "t3_1d6h5bp",
      "title": "Maldives will ban Israelis from entering the country over the war in Gaza",
      "link": "https://www.reddit.com/r/worldnews/comments/1d6h5bp/maldives_will_ban_israelis_from_entering_the/",
      "published": "2024-06-02T16:29:33.000Z",
      "description": "submitted by    /u/MintWiz   [link]   [comments]",
      "summary": "",
      "author": {
        "name": "/u/MintWiz",
        "uri": "https://www.reddit.com/user/MintWiz"
      },
      "category": {
        "@_term": "worldnews",
        "@_label": "r/worldnews"
      }
    },
    {
      "id": "t3_1d6f8kt",
      "title": "South Korea vows 'unbearable' retaliation against North Korea over its launch of trash balloons",
      "link": "https://www.reddit.com/r/worldnews/comments/1d6f8kt/south_korea_vows_unbearable_retaliation_against/",
      "published": "2024-06-02T15:01:40.000Z",
      "description": "submitted by    /u/CupidStunt13   [link]   [comments]",
      "summary": "",
      "author": {
        "name": "/u/CupidStunt13",
        "uri": "https://www.reddit.com/user/CupidStunt13"
      },
      "category": {
        "@_term": "worldnews",
        "@_label": "r/worldnews"
      }
    },
    {
      "id": "t3_1d6bvgj",
      "title": "Mexicans vote in election seen crowning first female president",
      "link": "https://www.reddit.com/r/worldnews/comments/1d6bvgj/mexicans_vote_in_election_seen_crowning_first/",
      "published": "2024-06-02T12:08:34.000Z",
      "description": "submitted by    /u/ntbfrosty   [link]   [comments]",
      "summary": "",
      "author": {
        "name": "/u/ntbfrosty",
        "uri": "https://www.reddit.com/user/ntbfrosty"
      },
      "category": {
        "@_term": "worldnews",
        "@_label": "r/worldnews"
      }
    },
    {
      "id": "t3_1d67muf",
      "title": "Crimean students’ grades lowered for not writing 'thank you letters' to Russian soldiers invading Ukraine",
      "link": "https://www.reddit.com/r/worldnews/comments/1d67muf/crimean_students_grades_lowered_for_not_writing/",
      "published": "2024-06-02T07:11:17.000Z",
      "description": "submitted by    /u/new974517   [link]   [comments]",
      "summary": "",
      "author": {
        "name": "/u/new974517",
        "uri": "https://www.reddit.com/user/new974517"
      },
      "category": {
        "@_term": "worldnews",
        "@_label": "r/worldnews"
      }
    },
    {
      "id": "t3_1d6e5e3",
      "title": "Israel shelved its original plan for Rafah due to American pressure",
      "link": "https://www.reddit.com/r/worldnews/comments/1d6e5e3/israel_shelved_its_original_plan_for_rafah_due_to/",
      "published": "2024-06-02T14:10:13.000Z",
      "description": "submitted by    /u/yuri_2022   [link]   [comments]",
      "summary": "",
      "author": {
        "name": "/u/yuri_2022",
        "uri": "https://www.reddit.com/user/yuri_2022"
      },
      "category": {
        "@_term": "worldnews",
        "@_label": "r/worldnews"
      }
    },
    {
      "id": "t3_1d66rf7",
      "title": "Russia loses record number of soldiers in May",
      "link": "https://www.reddit.com/r/worldnews/comments/1d66rf7/russia_loses_record_number_of_soldiers_in_may/",
      "published": "2024-06-02T06:11:28.000Z",
      "description": "submitted by    /u/kolbasar   [link]   [comments]",
      "summary": "",
      "author": {
        "name": "/u/kolbasar",
        "uri": "https://www.reddit.com/user/kolbasar"
      },
      "category": {
        "@_term": "worldnews",
        "@_label": "r/worldnews"
      }
    },
    {
      "id": "t3_1d6c649",
      "title": "Ukraine’s largest hydroelectric dam in critical condition after Russian strikes, authorities say",
      "link": "https://www.reddit.com/r/worldnews/comments/1d6c649/ukraines_largest_hydroelectric_dam_in_critical/",
      "published": "2024-06-02T12:25:47.000Z",
      "description": "submitted by    /u/ThunderFuryNinja   [link]   [comments]",
      "summary": "",
      "author": {
        "name": "/u/ThunderFuryNinja",
        "uri": "https://www.reddit.com/user/ThunderFuryNinja"
      },
      "category": {
        "@_term": "worldnews",
        "@_label": "r/worldnews"
      }
    },
    {
      "id": "t3_1d65t73",
      "title": "U.K. millennials will probably never see same income boom as elders, study shows",
      "link": "https://www.reddit.com/r/worldnews/comments/1d65t73/uk_millennials_will_probably_never_see_same/",
      "published": "2024-06-02T05:07:52.000Z",
      "description": "submitted by    /u/deadpools0   [link]   [comments]",
      "summary": "",
      "author": {
        "name": "/u/deadpools0",
        "uri": "https://www.reddit.com/user/deadpools0"
      },
      "category": {
        "@_term": "worldnews",
        "@_label": "r/worldnews"
      }
    },
    {
      "id": "t3_1d68d0a",
      "title": "Beijing ready to 'forcefully' stop Taiwan independence: China's defense chief",
      "link": "https://www.reddit.com/r/worldnews/comments/1d68d0a/beijing_ready_to_forcefully_stop_taiwan/",
      "published": "2024-06-02T08:04:03.000Z",
      "description": "submitted by    /u/NylaHowell9391   [link]   [comments]",
      "summary": "",
      "author": {
        "name": "/u/NylaHowell9391",
        "uri": "https://www.reddit.com/user/NylaHowell9391"
      },
      "category": {
        "@_term": "worldnews",
        "@_label": "r/worldnews"
      }
    },
    {
      "id": "t3_1d6g0v4",
      "title": "Mexicans vote in election likely to see first woman president",
      "link": "https://www.reddit.com/r/worldnews/comments/1d6g0v4/mexicans_vote_in_election_likely_to_see_first/",
      "published": "2024-06-02T15:38:13.000Z",
      "description": "submitted by    /u/SendStoreMeloner   [link]   [comments]",
      "summary": "",
      "author": {
        "name": "/u/SendStoreMeloner",
        "uri": "https://www.reddit.com/user/SendStoreMeloner"
      },
      "category": {
        "@_term": "worldnews",
        "@_label": "r/worldnews"
      }
    },
    {
      "id": "t3_1d6hroo",
      "title": "France, Britain and Norway Search for Russian Submarine off Irish West Coast",
      "link": "https://www.reddit.com/r/worldnews/comments/1d6hroo/france_britain_and_norway_search_for_russian/",
      "published": "2024-06-02T16:58:29.000Z",
      "description": "submitted by    /u/MGC91   [link]   [comments]",
      "summary": "",
      "author": {
        "name": "/u/MGC91",
        "uri": "https://www.reddit.com/user/MGC91"
      },
      "category": {
        "@_term": "worldnews",
        "@_label": "r/worldnews"
      }
    },
    {
      "id": "t3_1d67kp5",
      "title": "George Clooney Foundation to seek arrest of Russian propagandists",
      "link": "https://www.reddit.com/r/worldnews/comments/1d67kp5/george_clooney_foundation_to_seek_arrest_of/",
      "published": "2024-06-02T07:07:21.000Z",
      "description": "submitted by    /u/new974517   [link]   [comments]",
      "summary": "",
      "author": {
        "name": "/u/new974517",
        "uri": "https://www.reddit.com/user/new974517"
      },
      "category": {
        "@_term": "worldnews",
        "@_label": "r/worldnews"
      }
    },
    {
      "id": "t3_1d6djjb",
      "title": "Zelensky accuses Russia and China of undermining summit",
      "link": "https://www.reddit.com/r/worldnews/comments/1d6djjb/zelensky_accuses_russia_and_china_of_undermining/",
      "published": "2024-06-02T13:39:50.000Z",
      "description": "submitted by    /u/Gyro_Armadillo   [link]   [comments]",
      "summary": "",
      "author": {
        "name": "/u/Gyro_Armadillo",
        "uri": "https://www.reddit.com/user/Gyro_Armadillo"
      },
      "category": {
        "@_term": "worldnews",
        "@_label": "r/worldnews"
      }
    },
    {
      "id": "t3_1d6a9na",
      "title": "Jail time for those caught distributing deepfake porn under new Australian laws",
      "link": "https://www.reddit.com/r/worldnews/comments/1d6a9na/jail_time_for_those_caught_distributing_deepfake/",
      "published": "2024-06-02T10:24:03.000Z",
      "description": "submitted by    /u/javelin3000   [link]   [comments]",
      "summary": "",
      "author": {
        "name": "/u/javelin3000",
        "uri": "https://www.reddit.com/user/javelin3000"
      },
      "category": {
        "@_term": "worldnews",
        "@_label": "r/worldnews"
      }
    },
    {
      "id": "t3_1d6fvsf",
      "title": "China says Philippine personnel pointed guns at Chinese coast guard in disputed waters",
      "link": "https://www.reddit.com/r/worldnews/comments/1d6fvsf/china_says_philippine_personnel_pointed_guns_at/",
      "published": "2024-06-02T15:31:38.000Z",
      "description": "submitted by    /u/just-another-schmoe   [link]   [comments]",
      "summary": "",
      "author": {
        "name": "/u/just-another-schmoe",
        "uri": "https://www.reddit.com/user/just-another-schmoe"
      },
      "category": {
        "@_term": "worldnews",
        "@_label": "r/worldnews"
      }
    },
    {
      "id": "t3_1d6a9pn",
      "title": "Biden's Gaza plan 'not a good deal' but Israel accepts it, Netanyahu aide says",
      "link": "https://www.reddit.com/r/worldnews/comments/1d6a9pn/bidens_gaza_plan_not_a_good_deal_but_israel/",
      "published": "2024-06-02T10:24:10.000Z",
      "description": "submitted by    /u/HenzShuyi   [link]   [comments]",
      "summary": "",
      "author": {
        "name": "/u/HenzShuyi",
        "uri": "https://www.reddit.com/user/HenzShuyi"
      },
      "category": {
        "@_term": "worldnews",
        "@_label": "r/worldnews"
      }
    },
    {
      "id": "t3_1d6mu5l",
      "title": "At least 33 Indian polling staff died on the last day of voting from heatstroke in just one state, a top election official said Sunday, after scorching temperatures gripped swathes of the country",
      "link": "https://www.reddit.com/r/worldnews/comments/1d6mu5l/at_least_33_indian_polling_staff_died_on_the_last/",
      "published": "2024-06-02T20:40:36.000Z",
      "description": "submitted by    /u/DoremusJessup   [link]   [comments]",
      "summary": "",
      "author": {
        "name": "/u/DoremusJessup",
        "uri": "https://www.reddit.com/user/DoremusJessup"
      },
      "category": {
        "@_term": "worldnews",
        "@_label": "r/worldnews"
      }
    },
    {
      "id": "t3_1d6ehw8",
      "title": "Panama prepares to evacuate first island in face of rising sea levels",
      "link": "https://www.reddit.com/r/worldnews/comments/1d6ehw8/panama_prepares_to_evacuate_first_island_in_face/",
      "published": "2024-06-02T14:26:41.000Z",
      "description": "submitted by    /u/theluckyfrog   [link]   [comments]",
      "summary": "",
      "author": {
        "name": "/u/theluckyfrog",
        "uri": "https://www.reddit.com/user/theluckyfrog"
      },
      "category": {
        "@_term": "worldnews",
        "@_label": "r/worldnews"
      }
    },
    {
      "id": "t3_1d5xdw2",
      "title": "Japan loses contact with Akatsuki, humanity's only active Venus probe",
      "link": "https://www.reddit.com/r/worldnews/comments/1d5xdw2/japan_loses_contact_with_akatsuki_humanitys_only/",
      "published": "2024-06-01T21:30:42.000Z",
      "description": "submitted by    /u/jimi15   [link]   [comments]",
      "summary": "",
      "author": {
        "name": "/u/jimi15",
        "uri": "https://www.reddit.com/user/jimi15"
      },
      "category": {
        "@_term": "worldnews",
        "@_label": "r/worldnews"
      }
    },
    {
      "id": "t3_1d63799",
      "title": "'Biden is our only hope': Thousands of Israelis urge hostage deal",
      "link": "https://www.reddit.com/r/worldnews/comments/1d63799/biden_is_our_only_hope_thousands_of_israelis_urge/",
      "published": "2024-06-02T02:28:36.000Z",
      "description": "submitted by    /u/DoremusJessup   [link]   [comments]",
      "summary": "",
      "author": {
        "name": "/u/DoremusJessup",
        "uri": "https://www.reddit.com/user/DoremusJessup"
      },
      "category": {
        "@_term": "worldnews",
        "@_label": "r/worldnews"
      }
    },
    {
      "id": "t3_1d6mwug",
      "title": "Thousands of protesters rallied in Istanbul Sunday in outrage at the Turkish government's proposals to put down stray dogs, yelling: \"No to the massacre!\"",
      "link": "https://www.reddit.com/r/worldnews/comments/1d6mwug/thousands_of_protesters_rallied_in_istanbul/",
      "published": "2024-06-02T20:43:44.000Z",
      "description": "submitted by    /u/DoremusJessup   [link]   [comments]",
      "summary": "",
      "author": {
        "name": "/u/DoremusJessup",
        "uri": "https://www.reddit.com/user/DoremusJessup"
      },
      "category": {
        "@_term": "worldnews",
        "@_label": "r/worldnews"
      }
    },
    {
      "id": "t3_1d686fm",
      "title": "Mayoral candidate in Tamaulipas Mexico dies a day before the elections after a palm tree falls on him",
      "link": "https://www.reddit.com/r/worldnews/comments/1d686fm/mayoral_candidate_in_tamaulipas_mexico_dies_a_day/",
      "published": "2024-06-02T07:50:52.000Z",
      "description": "submitted by    /u/Spascucci   [link]   [comments]",
      "summary": "",
      "author": {
        "name": "/u/Spascucci",
        "uri": "https://www.reddit.com/user/Spascucci"
      },
      "category": {
        "@_term": "worldnews",
        "@_label": "r/worldnews"
      }
    },
    {
      "id": "t3_1d66plp",
      "title": "North Korea sends 600 more trash balloons over border, South says",
      "link": "https://www.reddit.com/r/worldnews/comments/1d66plp/north_korea_sends_600_more_trash_balloons_over/",
      "published": "2024-06-02T06:08:04.000Z",
      "description": "submitted by    /u/Krumecabe   [link]   [comments]",
      "summary": "",
      "author": {
        "name": "/u/Krumecabe",
        "uri": "https://www.reddit.com/user/Krumecabe"
      },
      "category": {
        "@_term": "worldnews",
        "@_label": "r/worldnews"
      }
    },
    {
      "id": "t3_1d6a8vq",
      "title": "Zelensky says China’s ‘support to Russia’ will extend war in Ukraine during surprise appearance in Asia | CNN",
      "link": "https://www.reddit.com/r/worldnews/comments/1d6a8vq/zelensky_says_chinas_support_to_russia_will/",
      "published": "2024-06-02T10:22:32.000Z",
      "description": "submitted by    /u/javelin3000   [link]   [comments]",
      "summary": "",
      "author": {
        "name": "/u/javelin3000",
        "uri": "https://www.reddit.com/user/javelin3000"
      },
      "category": {
        "@_term": "worldnews",
        "@_label": "r/worldnews"
      }
    }
  ]
}